sema4ai_docint/__init__.py
sema4ai_docint/logging.py
sema4ai_docint/py.typed
sema4ai_docint/utils.py
sema4ai_docint/agent_server_client/README.md
sema4ai_docint/agent_server_client/__init__.py
sema4ai_docint/agent_server_client/client.py
sema4ai_docint/agent_server_client/docx_to_markdown.py
sema4ai_docint/agent_server_client/exceptions.py
sema4ai_docint/agent_server_client/images.py
sema4ai_docint/agent_server_client/models.py
sema4ai_docint/agent_server_client/prompts.py
sema4ai_docint/agent_server_client/schema_validation.py
sema4ai_docint/agent_server_client/prompts/schema_prompt_template.jinja
sema4ai_docint/agent_server_client/transport/__init__.py
sema4ai_docint/agent_server_client/transport/base.py
sema4ai_docint/agent_server_client/transport/errors.py
sema4ai_docint/agent_server_client/transport/http.py
sema4ai_docint/agent_server_client/transport/memory.py
sema4ai_docint/extraction/README.md
sema4ai_docint/extraction/__init__.py
sema4ai_docint/extraction/process.py
sema4ai_docint/extraction/reducto/__init__.py
sema4ai_docint/extraction/reducto/async_.py
sema4ai_docint/extraction/reducto/client.py
sema4ai_docint/extraction/reducto/config.py
sema4ai_docint/extraction/reducto/exceptions.py
sema4ai_docint/extraction/reducto/sync.py
sema4ai_docint/extraction/transform/__init__.py
sema4ai_docint/extraction/transform/transform.py
sema4ai_docint/extraction/transform/transform_document_layout.py
sema4ai_docint/models/__init__.py
sema4ai_docint/models/constants.py
sema4ai_docint/models/data_model.py
sema4ai_docint/models/document.py
sema4ai_docint/models/document_layout.py
sema4ai_docint/models/document_v2.py
sema4ai_docint/models/extraction.py
sema4ai_docint/models/initialize.py
sema4ai_docint/models/mapping.py
sema4ai_docint/models/migration.py
sema4ai_docint/models/sql/pg_schema.sql
sema4ai_docint/models/sql/sqlite_schema.sql
sema4ai_docint/schemas/__init__.py
sema4ai_docint/schemas/data_model.py
sema4ai_docint/schemas/similarity.py
sema4ai_docint-0.12.0.dist-info/METADATA
sema4ai_docint-0.12.0.dist-info/WHEEL
sema4ai_docint-0.12.0.dist-info/licenses/LICENSE
sema4ai_docint-0.12.0.dist-info/RECORD
