Metadata-Version: 2.4
Name: sema4ai-docint
Version: 0.12.0
Summary: Sema4.ai Document Intelligence library
Author-email: Sema4ai Developers <engineering@sema4.ai>
License: Sema4.ai End User License Agreement
License-File: LICENSE
Requires-Python: <4.0,>=3.11
Requires-Dist: aiofiles>=24.1.0
Requires-Dist: aiohttp>=3.10.0
Requires-Dist: jinja2>=3.1.6
Requires-Dist: jsonschema>=4.0.0
Requires-Dist: mindsdb-sql==0.21.0
Requires-Dist: openpyxl>=3.1.5
Requires-Dist: pandas>=2.2.3
Requires-Dist: pillow>=10.0.0
Requires-Dist: pydantic<3,>=2.11
Requires-Dist: pymupdf>=1.24.10
Requires-Dist: python-docx==0.8.11
Requires-Dist: python-dotenv>=1.0.0
Requires-Dist: reductoai==0.9.0
Requires-Dist: requests>=2.32.3
Requires-Dist: scikit-learn>=1.7.0
Requires-Dist: sema4ai-actions<2,>=1.6.1
Requires-Dist: sema4ai-data<2,>=1.0.8
Requires-Dist: sema4ai-http-helper==2.1.0
Provides-Extra: memory
Requires-Dist: fastapi<0.116.0,>=0.115.6; extra == 'memory'
Requires-Dist: python-multipart>=0.0.6; extra == 'memory'
Requires-Dist: uvicorn<0.35.0,>=0.34.0; extra == 'memory'
